{
	"elements": [
		{
			"weight": 1.0,
			"key": {
				"Category": "monster",
				"Name": "rats:black_death"
			}
		},
		{
			"weight": 1.0,
			"key": {
				"Category": "monster",
				"Name": "rats:demon_rat"
			}
		},
		{
			"weight": 1.0,
			"key": {
				"Category": "monster",
				"Name": "rats:dutchrat"
			}
		},
		{
			"weight": 1.0,
			"key": {
				"Category": "monster",
				"Name": "rats:feral_ratlantean"
			}
		},
		{
			"weight": 1.0,
			"key": {
				"Category": "monster",
				"Name": "rats:ghost_pirat"
			}
		},
		{
			"weight": 1.0,
			"key": {
				"Category": "monster",
				"Name": "rats:neo_ratlantean"
			}
		},
		{
			"weight": 1.0,
			"key": {
				"Category": "monster",
				"Name": "rats:pied_piper"
			}
		},
		{
			"weight": 1.0,
			"key": {
				"Category": "monster",
				"Name": "rats:pirat"
			}
		},
		{
			"weight": 1.0,
			"key": {
				"Category": "monster",
				"Name": "rats:pirat_boat"
			}
		},
		{
			"weight": 1.0,
			"key": {
				"Category": "monster",
				"Name": "rats:plague_beast"
			}
		},
		{
			"weight": 1.0,
			"key": {
				"Category": "monster",
				"Name": "rats:plague_cloud"
			}
		},
		{
			"weight": 1.0,
			"key": {
				"Category": "creature",
				"Name": "rats:plague_doctor"
			}
		},
		{
			"weight": 1.0,
			"key": {
				"Category": "rats",
				"Name": "rats:rat"
			}
		},
		{
			"weight": 1.0,
			"key": {
				"Category": "monster",
				"Name": "rats:rat_baron"
			}
		},
		{
			"weight": 1.0,
			"key": {
				"Category": "monster",
				"Name": "rats:rat_baron_plane"
			}
		},
		{
			"weight": 1.0,
			"key": {
				"Category": "monster",
				"Name": "rats:rat_king"
			}
		},
		{
			"weight": 1.0,
			"key": {
				"Category": "water_ambient",
				"Name": "rats:ratfish"
			}
		},
		{
			"weight": 1.0,
			"key": {
				"Category": "monster",
				"Name": "rats:ratlantean_automaton"
			}
		},
		{
			"weight": 1.0,
			"key": {
				"Category": "monster",
				"Name": "rats:ratlantean_ratbot"
			}
		},
		{
			"weight": 1.0,
			"key": {
				"Category": "monster",
				"Name": "rats:ratlantean_spirit"
			}
		},
		{
			"weight": 1.0,
			"key": {
				"Category": "rats",
				"Name": "rats:tamed_rat"
			}
		}
	]
}
