{
	"elements": [
		{
			"weight": 1.0,
			"key": {
				"Category": "creature",
				"Name": "undergarden:brute"
			}
		},
		{
			"weight": 1.0,
			"key": {
				"Category": "creature",
				"Name": "undergarden:dweller"
			}
		},
		{
			"weight": 1.0,
			"key": {
				"Category": "monster",
				"Name": "undergarden:forgotten"
			}
		},
		{
			"weight": 1.0,
			"key": {
				"Category": "monster",
				"Name": "undergarden:forgotten_guardian"
			}
		},
		{
			"weight": 1.0,
			"key": {
				"Category": "creature",
				"Name": "undergarden:gloomper"
			}
		},
		{
			"weight": 1.0,
			"key": {
				"Category": "water_creature",
				"Name": "undergarden:gwib"
			}
		},
		{
			"weight": 1.0,
			"key": {
				"Category": "water_ambient",
				"Name": "undergarden:gwibling"
			}
		},
		{
			"weight": 1.0,
			"key": {
				"Category": "creature",
				"Name": "undergarden:mog"
			}
		},
		{
			"weight": 1.0,
			"key": {
				"Category": "monster",
				"Name": "undergarden:muncher"
			}
		},
		{
			"weight": 1.0,
			"key": {
				"Category": "monster",
				"Name": "undergarden:nargoyle"
			}
		},
		{
			"weight": 1.0,
			"key": {
				"Category": "monster",
				"Name": "undergarden:rotbeast"
			}
		},
		{
			"weight": 1.0,
			"key": {
				"Category": "monster",
				"Name": "undergarden:rotling"
			}
		},
		{
			"weight": 1.0,
			"key": {
				"Category": "monster",
				"Name": "undergarden:rotwalker"
			}
		},
		{
			"weight": 1.0,
			"key": {
				"Category": "ambient",
				"Name": "undergarden:scintling"
			}
		},
		{
			"weight": 1.0,
			"key": {
				"Category": "creature",
				"Name": "undergarden:smog_mog"
			}
		},
		{
			"weight": 1.0,
			"key": {
				"Category": "monster",
				"Name": "undergarden:sploogie"
			}
		},
		{
			"weight": 1.0,
			"key": {
				"Category": "monster",
				"Name": "undergarden:stoneborn"
			}
		}
	]
}
