{
	"elements": [
		{
			"weight": 1.0,
			"key": {
				"top": true,
				"laggy": false,
				"float": true,
				"Name": "sons_of_sins:block_of_blazing_hearts",
				"full": true
			}
		},
		{
			"weight": 1.0,
			"key": {
				"top": true,
				"laggy": false,
				"float": true,
				"Name": "sons_of_sins:block_of_creeper_ribs",
				"full": true
			}
		},
		{
			"weight": 1.0,
			"key": {
				"top": true,
				"laggy": false,
				"float": true,
				"Name": "sons_of_sins:block_of_enderman_muscles",
				"full": true
			}
		},
		{
			"weight": 1.0,
			"key": {
				"top": true,
				"laggy": false,
				"float": true,
				"Name": "sons_of_sins:block_of_golem_cuirass",
				"full": true
			}
		},
		{
			"weight": 1.0,
			"key": {
				"top": true,
				"laggy": false,
				"float": true,
				"Name": "sons_of_sins:block_of_hearts",
				"full": true
			}
		},
		{
			"weight": 1.0,
			"key": {
				"top": true,
				"laggy": false,
				"float": true,
				"Name": "sons_of_sins:block_of_ice_heart",
				"full": true
			}
		},
		{
			"weight": 1.0,
			"key": {
				"top": true,
				"laggy": false,
				"float": true,
				"Name": "sons_of_sins:block_of_muscles",
				"full": true
			}
		},
		{
			"weight": 1.0,
			"key": {
				"top": true,
				"laggy": false,
				"float": true,
				"Name": "sons_of_sins:block_of_ravager_muscle",
				"full": true
			}
		},
		{
			"weight": 1.0,
			"key": {
				"top": true,
				"laggy": false,
				"float": true,
				"Name": "sons_of_sins:block_of_ribs",
				"full": true
			}
		},
		{
			"weight": 1.0,
			"key": {
				"top": true,
				"laggy": false,
				"float": true,
				"Name": "sons_of_sins:block_of_slime_rear",
				"full": true
			}
		},
		{
			"weight": 1.0,
			"key": {
				"top": true,
				"laggy": false,
				"float": true,
				"Name": "sons_of_sins:block_of_spider_heart",
				"full": true
			}
		},
		{
			"weight": 1.0,
			"key": {
				"top": true,
				"laggy": false,
				"float": true,
				"Name": "sons_of_sins:block_of_strider_muscle",
				"full": true
			}
		},
		{
			"weight": 1.0,
			"key": {
				"top": true,
				"laggy": false,
				"float": true,
				"Name": "sons_of_sins:flesh_block",
				"full": false
			}
		},
		{
			"weight": 1.0,
			"key": {
				"top": true,
				"laggy": false,
				"float": true,
				"Name": "sons_of_sins:soul_steel_block",
				"full": true
			}
		},
		{
			"weight": 1.0,
			"key": {
				"top": true,
				"laggy": false,
				"float": true,
				"Name": "sons_of_sins:soul_steel_slab",
				"full": false
			}
		},
		{
			"weight": 1.0,
			"key": {
				"top": true,
				"laggy": false,
				"float": true,
				"Name": "sons_of_sins:soul_steel_stairs",
				"full": false
			}
		},
		{
			"weight": 1.0,
			"key": {
				"top": true,
				"laggy": false,
				"float": true,
				"Name": "sons_of_sins:soul_steel_tiles",
				"full": true
			}
		},
		{
			"weight": 1.0,
			"key": {
				"top": true,
				"laggy": true,
				"float": true,
				"Name": "sons_of_sins:urn_block",
				"full": false
			}
		}
	]
}
